{
  "students": [
    {
      "id": "1",
      "name": "James Smith"
    },
    {
      "id": "2",
      "name": "Olivia Johnson"
    },
    {
      "id": "3",
      "name": "Liam Brown"
    },
    {
      "id": "4",
      "name": "Emma Williams"
    },
    {
      "id": "5",
      "name": "Noah Jones"
    },
    {
      "id": "6",
      "name": "Sophia Garcia"
    },
    {
      "id": "7",
      "name": "Lucas Miller"
    },
    {
      "id": "8",
      "name": "Mia Davis"
    },
    {
      "id": "9",
      "name": "Ethan Martinez"
    },
    {
      "id": "10",
      "name": "Ava Rodriguez"
    },
    {
      "id": "5135",
      "name": "Eliud Sharks"
    },
    {
      "id": "4d17",
      "name": "Ian Kabaka"
    },
    {
      "id": "aae5",
      "name": "Saphia   mohammed"
    }
  ]
}